twod_analysis_kit-1.3.0.dist-info/licenses/AUTHORS.md
twod_analysis_kit-1.3.0.dist-info/licenses/LICENSE
twodanalysis/BioPolymer2D.py
twodanalysis/Cumulative2D.py
twodanalysis/MembProp.py
twodanalysis/Packing.py
twodanalysis/Voronoi2D.py
twodanalysis/__init__.py
twodanalysis/analysis.py
twodanalysis/data/README.md
twodanalysis/data/__init__.py
twodanalysis/data/files.py
twodanalysis/data/mda.txt
twodanalysis/examples/Test_ClassBioPolymer2D.py
twodanalysis/examples/Tests_BioPolymer2D.py
twodanalysis/tests/__init__.py
twodanalysis/tests/conftest.py
twodanalysis/tests/not_test_cases.py
twodanalysis/tests/test_biopolymer_2d.py
twodanalysis/tests/test_cumulative.py
twodanalysis/tests/test_membprop.py
twodanalysis/tests/test_packing.py
twodanalysis/tests/test_twodanalysis.py
twodanalysis/tests/test_voronoi.py
twodanalysis/tests/utils.py
twod_analysis_kit-1.3.0.dist-info/METADATA
twod_analysis_kit-1.3.0.dist-info/WHEEL
twod_analysis_kit-1.3.0.dist-info/top_level.txt
twod_analysis_kit-1.3.0.dist-info/RECORD
