Metadata-Version: 2.4
Name: twod-analysis-kit
Version: 1.3.0
Summary: Project created to study lipid membranes in a 2D fashion.
Author-email: "Ricardo Ramirez, Antonio Bosch, Ruben Perez, Horacio V Guzman, and Viviana Monje" <vmonje@buffalo.edu>
Maintainer-email: "Ricardo Ramirez, Antonio Bosch, Ruben Perez, Horacio V Guzman, and Viviana Monje" <vmonje@buffalo.edu>
License:                     GNU GENERAL PUBLIC LICENSE
Project-URL: source, https://github.com/monjegroup/twod-analysis-kit
Project-URL: documentation, https://twodanalysis.readthedocs.io/
Keywords: molecular simulations
Requires-Python: >=3.9
License-File: LICENSE
License-File: AUTHORS.md
Requires-Dist: MDAnalysis==2.7.0
Requires-Dist: imageio>=2.36.0
Requires-Dist: pandas
Requires-Dist: seaborn
Requires-Dist: networkx
Requires-Dist: numpy
Provides-Extra: test
Requires-Dist: pytest>=6.0; extra == "test"
Requires-Dist: pytest-xdist>=2.5; extra == "test"
Requires-Dist: pytest-cov>=3.0; extra == "test"
Requires-Dist: pooch; extra == "test"
Provides-Extra: doc
Requires-Dist: sphinx; extra == "doc"
Requires-Dist: sphinx_rtd_theme; extra == "doc"
Dynamic: license-file
